{
  "Sorcerer - ClefJ's Winterhold Patch": {
    "nexusmods": {
      "game_name": "skyrimspecialedition",
      "version": "1.0.0",
      "file_id": 404709,
      "file_name": "Sorcerer - ClefJ's Winterhold Patch-95212-1-0-0-1688741677.7z",
      "mod_id": 95212,
      "hash": "sha256-jZ1VKmucra7jd3mYcy+yQLtNy3cLMG7d13Nk9+s1Oj4="
    }
  },
  "Sorcerer - COTN Winterhold Patch": {
    "nexusmods": {
      "game_name": "skyrimspecialedition",
      "version": "1.0.0",
      "file_id": 404710,
      "file_name": "Sorcerer - COTN Winterhold Patch-95212-1-0-0-1688741743.7z",
      "mod_id": 95212,
      "hash": "sha256-Bu2qMEs77FpMhb9H46OPig5MaFkZ64mPXYK+4LVLqek="
    }
  },
  "Sorcerer - Distinct Interiors Patch": {
    "nexusmods": {
      "game_name": "skyrimspecialedition",
      "version": "1.0.0",
      "file_id": 404711,
      "file_name": "Sorcerer - Distinct Interiors Patch-95212-1-0-0-1688741782.7z",
      "mod_id": 95212,
      "hash": "sha256-HDk2TunMwqrDRth4AtQm3JrJRDkRA6iPO4ieJDslfQg="
    }
  },
  "Sorcerer - ELFX Patch": {
    "nexusmods": {
      "game_name": "skyrimspecialedition",
      "version": "1.0.0",
      "file_id": 404712,
      "file_name": "Sorcerer - ELFX Patch-95212-1-0-0-1688741824.7z",
      "mod_id": 95212,
      "hash": "sha256-nGvMxbLe1ERC8AG2lEP/Xix/cE1OXOpBhIYK3Z3vvsc="
    }
  },
  "Sorcerer - ICOW Patch": {
    "nexusmods": {
      "game_name": "skyrimspecialedition",
      "version": "1.0.0",
      "file_id": 404713,
      "file_name": "Sorcerer - ICOW Patch-95212-1-0-0-1688741872.7z",
      "mod_id": 95212,
      "hash": "sha256-Mns44fMNKA77rq28EDJFS+A4GLEQ85Jf/0lVxm0tt6A="
    }
  },
  "Sorcerer - InnCredible Patch": {
    "nexusmods": {
      "game_name": "skyrimspecialedition",
      "version": "1.0.0",
      "file_id": 404715,
      "file_name": "Sorcerer - InnCredible Patch-95212-1-0-0-1688741960.7z",
      "mod_id": 95212,
      "hash": "sha256-HvXKieqiRiq6Oe5DLZw0tX84TCki3lPIHjylDQ59kOM="
    }
  },
  "Sorcerer - Midden Expanded Patch": {
    "nexusmods": {
      "game_name": "skyrimspecialedition",
      "version": "1.0.0",
      "file_id": 404716,
      "file_name": "Sorcerer - Midden Expanded Patch-95212-1-0-0-1688741999.7z",
      "mod_id": 95212,
      "hash": "sha256-rmuBRDhMfztytsEGQKNNYfZWvPDcGuYE0bwTvn5zChs="
    }
  },
  "Sorcerer - OCW Patch": {
    "nexusmods": {
      "game_name": "skyrimspecialedition",
      "version": "1.0.0",
      "file_id": 404718,
      "file_name": "Sorcerer - OCW Patch-95212-1-0-0-1688742098.7z",
      "mod_id": 95212,
      "hash": "sha256-mBNcTbIfRFBCIhrr920LE1oQVlZD+GkAi9tnt2yCFv4="
    }
  },
  "Sorcerer - SFCO Patch": {
    "nexusmods": {
      "game_name": "skyrimspecialedition",
      "version": "1.0.0",
      "file_id": 404719,
      "file_name": "Sorcerer - SFCO Patch-95212-1-0-0-1688742133.7z",
      "mod_id": 95212,
      "hash": "sha256-4UK8rtymIoD3ulYsInvBtO7ROA+PusZixRwzSrcU/Jk="
    }
  },
  "Sorcerer - The Great Cities - Minor Cities Patch": {
    "nexusmods": {
      "game_name": "skyrimspecialedition",
      "version": "1.0.0",
      "file_id": 404720,
      "file_name": "Sorcerer - The Great Cities - Minor Cities Patch-95212-1-0-0-1688742206.7z",
      "mod_id": 95212,
      "hash": "sha256-Bzkndk8fdkof7An0nIfrrDOLaU6DYtnwXcBIep4x06Q="
    }
  },
  "Sorcerer - The Great City of Winterhold Patch": {
    "nexusmods": {
      "game_name": "skyrimspecialedition",
      "version": "1.0.0",
      "file_id": 404721,
      "file_name": "Sorcerer - The Great City of Winterhold Patch-95212-1-0-0-1688742240.7z",
      "mod_id": 95212,
      "hash": "sha256-KdueICzKUt9BW4rAHpY9oo1JRteEzlbdh7IO5hQgy9w="
    }
  },
  "Sorcerer - JK's COW - OCW Patch": {
    "nexusmods": {
      "game_name": "skyrimspecialedition",
      "version": "1.0.0",
      "file_id": 404725,
      "file_name": "Sorcerer - JK's COW - OCW Patch-95212-1-0-0-1688742371.7z",
      "mod_id": 95212,
      "hash": "sha256-X6gs5QXYQiFkqxx8chI0EuBhClCXFPi7F+lUzDEbZHg="
    }
  },
  "Sorcerer - UCOW Patch": {
    "nexusmods": {
      "game_name": "skyrimspecialedition",
      "version": "1.0.0",
      "file_id": 404726,
      "file_name": "Sorcerer - UCOW Patch-95212-1-0-0-1688742415.7z",
      "mod_id": 95212,
      "hash": "sha256-064Yr8DSQBrt6x7DO1q1MssEhh19K8WI2ZaY1TVPIbA="
    }
  },
  "Sorcerer - JK COW - ICOW Patch": {
    "nexusmods": {
      "game_name": "skyrimspecialedition",
      "version": "1.0.1",
      "file_id": 406067,
      "file_name": "Sorcerer - JK COW - ICOW Patch-95212-1-0-1-1689050182.7z",
      "mod_id": 95212,
      "hash": "sha256-qAsMgTfp0b1x+00rRYFc4rMX2i+ko3TedtFqQzKfxFk="
    }
  },
  "Sorcerer - JK's COW Patch": {
    "nexusmods": {
      "game_name": "skyrimspecialedition",
      "version": "1.0.1",
      "file_id": 406068,
      "file_name": "Sorcerer - JK's COW Patch-95212-1-0-1-1689050271.7z",
      "mod_id": 95212,
      "hash": "sha256-76JJhqqSlX1pAxiwdw1xSGnxQRD8+N3HWYecDtnrXDM="
    }
  },
  "Sorcerer Synthesis Patcher": {
    "nexusmods": {
      "game_name": "skyrimspecialedition",
      "version": "1.0.12",
      "file_id": 496517,
      "file_name": "Sorcerer Synthesis Patcher-95212-1-0-12-1714509718.7z",
      "mod_id": 95212,
      "hash": "sha256-PbtpDFvKt2qjSLx9BwHbLcMu4Dpf/ZU2tkZ4lEX3WjA="
    },
    "type": "primary"
  }
}