{
  "Temper Replicas for Volkihar Knight Armor": {
    "nexusmods": {
      "game_name": "skyrimspecialedition",
      "version": "1",
      "file_id": 152567,
      "file_name": "Temper Replicas for Volkihard Knight Armor-37553-1-1595941996.7z",
      "mod_id": 37553,
      "hash": "sha256-7NZKIrlK8+wuClKR2yCyJCJ0DAzildSZDrwr0xvan8A="
    }
  },
  "Temper Replicas for The Curator's Companion": {
    "nexusmods": {
      "game_name": "skyrimspecialedition",
      "version": "1",
      "file_id": 177543,
      "file_name": "Temper Replicas for The Curator's Companion-37553-1-1609696288.7z",
      "mod_id": 37553,
      "hash": "sha256-s6F4uPCqAvwuQXMFQTUDLmfknwwt+tZAq0c7o4Ev9Ko="
    }
  },
  "Temper Replicas - Main File": {
    "nexusmods": {
      "game_name": "skyrimspecialedition",
      "version": "1.3.2",
      "file_id": 690774,
      "file_name": "Temper Replicas - Main File-37553-1-3-2-1763996148.7z",
      "mod_id": 37553,
      "hash": "sha256-h3HanDj0DEgdDOZpz+EZj7OIb/FJ1Z32+/aqs012YWI="
    },
    "type": "primary"
  }
}